pepedd/nodes/__init__.py
pepedd/nodes/blur/__init__.py
pepedd/nodes/blur/blur.py
pepedd/nodes/blur/schemas.py
pepedd/nodes/compress/__init__.py
pepedd/nodes/compress/comp_funcs.py
pepedd/nodes/compress/comp_maps.py
pepedd/nodes/compress/compress.py
pepedd/nodes/compress/schemas.py
pepedd/nodes/compress/video.py
pepedd/nodes/dithering/__init__.py
pepedd/nodes/dithering/dithering.py
pepedd/nodes/dithering/quantizer.py
pepedd/nodes/dithering/schemas.py
pepedd/nodes/halo/__init__.py
pepedd/nodes/halo/halo.py
pepedd/nodes/halo/schemas.py
pepedd/nodes/lines/__init__.py
pepedd/nodes/lines/lines.py
pepedd/nodes/lines/lines_funcs.py
pepedd/nodes/lines/schemas.py
pepedd/nodes/resize/__init__.py
pepedd/nodes/resize/resize.py
pepedd/nodes/resize/schemas.py
pepedd/nodes/utils/__init__.py
pepedd/nodes/utils/constants.py
pepedd/nodes/utils/custom_random.py
pepedd/nodes/utils/validate.py
pepedd/nodes/utils/custom_blur/__init__.py
pepedd/nodes/utils/custom_blur/astropy.py
pepedd/nodes/utils/custom_blur/box_blur.py
pepedd/nodes/utils/custom_blur/gauss.py
pepedd/nodes/utils/custom_blur/lens_blur.py
pepedd/nodes/utils/custom_blur/motion_blur.py
pepedd/nodes/utils/custom_blur/rkernel_blur.py
pepedd_nodes-0.1.1.dist-info/METADATA
pepedd_nodes-0.1.1.dist-info/WHEEL
pepedd_nodes-0.1.1.dist-info/top_level.txt
pepedd_nodes-0.1.1.dist-info/RECORD
