Metadata-Version: 2.4
Name: pepedd-nodes
Version: 0.1.1
Summary: Additional nodes for pepedd
Requires-Python: >=3.11
Requires-Dist: pepedd>=0.1.0
Requires-Dist: astropy~=7.2.0
Requires-Dist: chainner-ext~=0.3.10
Requires-Dist: colour-science~=0.4.7
Requires-Dist: opencv-python~=4.11.0.86
Requires-Dist: pepedpid~=0.1.1
Requires-Dist: scikit-image~=0.26.0
Requires-Dist: scipy~=1.16.3
